{"card":{"id":"xy7-92","name":"M Tyranitar-EX","nationalPokedexNumber":248,"imageUrl":"https://s3.amazonaws.com/pokemontcg/xy7/92.png","subtype":"MEGA","supertype":"Pokémon","hp":"240","retreatCost":["Colorless","Colorless","Colorless","Colorless"],"number":"92","artist":"5ban Graphics","rarity":"Rare Ultra","series":"XY","set":"Ancient Origins","setCode":"xy7","text":["When a Pokémon-EX has been Knocked Out, your opponent takes 2 Prize cards.","This Pokémon may have up to 2 Pokémon Tool cards attached to it.","When 1 of your Pokémon becomes a Mega Evolution Pokémon, your turn ends."],"types":["Darkness"],"attacks":[{"cost":["Darkness","Darkness","Colorless","Colorless"],"name":"Destroyer King","text":"This attack does 60 more damage for each damage counter on your opponent's Active Pokémon.","damage":"110+","convertedEnergyCost":4}],"weaknesses":[{"type":"Fighting","value":"×2"}],"resistances":[{"type":"Psychic","value":"-20"}]}}